foco/__init__.py
foco/example.py
foco-0.0.1.dist-info/METADATA
foco-0.0.1.dist-info/WHEEL
foco-0.0.1.dist-info/RECORD
